odoo/addons/fieldservice_account_analytic/README.rst
odoo/addons/fieldservice_account_analytic/__init__.py
odoo/addons/fieldservice_account_analytic/__manifest__.py
odoo/addons/fieldservice_account_analytic/init_hook.py
odoo/addons/fieldservice_account_analytic/data/ir_rule.xml
odoo/addons/fieldservice_account_analytic/demo/fsm_location.xml
odoo/addons/fieldservice_account_analytic/i18n/es.po
odoo/addons/fieldservice_account_analytic/i18n/es_AR.po
odoo/addons/fieldservice_account_analytic/i18n/es_CL.po
odoo/addons/fieldservice_account_analytic/i18n/fieldservice_account_analytic.pot
odoo/addons/fieldservice_account_analytic/i18n/it.po
odoo/addons/fieldservice_account_analytic/i18n/pt_BR.po
odoo/addons/fieldservice_account_analytic/i18n/pt_PT.po
odoo/addons/fieldservice_account_analytic/i18n/tr.po
odoo/addons/fieldservice_account_analytic/migrations/14.0.1.0.0/post-migration.py
odoo/addons/fieldservice_account_analytic/models/__init__.py
odoo/addons/fieldservice_account_analytic/models/account_move.py
odoo/addons/fieldservice_account_analytic/models/analytic_account.py
odoo/addons/fieldservice_account_analytic/models/fsm_location.py
odoo/addons/fieldservice_account_analytic/models/fsm_order.py
odoo/addons/fieldservice_account_analytic/models/res_company.py
odoo/addons/fieldservice_account_analytic/models/res_config_settings.py
odoo/addons/fieldservice_account_analytic/readme/CONFIGURE.rst
odoo/addons/fieldservice_account_analytic/readme/CONTRIBUTORS.rst
odoo/addons/fieldservice_account_analytic/readme/CREDITS.rst
odoo/addons/fieldservice_account_analytic/readme/DESCRIPTION.rst
odoo/addons/fieldservice_account_analytic/readme/INSTALL.rst
odoo/addons/fieldservice_account_analytic/readme/USAGE.rst
odoo/addons/fieldservice_account_analytic/report/fsm_order_report_template.xml
odoo/addons/fieldservice_account_analytic/security/ir.model.access.csv
odoo/addons/fieldservice_account_analytic/static/description/icon.png
odoo14_addon_fieldservice_account_analytic-14.0.1.0.1.dist-info/METADATA
odoo14_addon_fieldservice_account_analytic-14.0.1.0.1.dist-info/WHEEL
odoo14_addon_fieldservice_account_analytic-14.0.1.0.1.dist-info/top_level.txt
odoo14_addon_fieldservice_account_analytic-14.0.1.0.1.dist-info/RECORD
